datasette_current_actor/__init__.py
datasette_current_actor-0.3.dist-info/LICENSE
datasette_current_actor-0.3.dist-info/METADATA
datasette_current_actor-0.3.dist-info/WHEEL
datasette_current_actor-0.3.dist-info/entry_points.txt
datasette_current_actor-0.3.dist-info/top_level.txt
datasette_current_actor-0.3.dist-info/RECORD
