Metadata-Version: 2.1
Name: datasette-current-actor
Version: 0.3
Summary: Adds a current_actor() function to SQLite that show's the current actor's ID.
Home-page: https://github.com/cldellow/datasette-current-actor
Author: Colin Dellow
License: Apache License, Version 2.0
Project-URL: Issues, https://github.com/cldellow/datasette-current-actor/issues
Project-URL: CI, https://github.com/cldellow/datasette-current-actor/actions
Project-URL: Changelog, https://github.com/cldellow/datasette-current-actor/releases
Classifier: Framework :: Datasette
Classifier: License :: OSI Approved :: Apache Software License
Requires-Python: >=3.7
License-File: LICENSE
Requires-Dist: datasette (>=1.0a0)
Provides-Extra: test
Requires-Dist: pytest ; extra == 'test'
Requires-Dist: pytest-asyncio ; extra == 'test'
Requires-Dist: pytest-watch ; extra == 'test'
